{
  "entries": [
    {
      "item": "minecraft:beef",
      "emc": 64
    },
    {
      "item": "minecraft:cooked_beef",
      "emc": 64
    },
    {
      "item": "minecraft:porkchop",
      "emc": 64
    },
    {
      "item": "minecraft:cooked_porkchop",
      "emc": 64
    },
    {
      "item": "minecraft:mutton",
      "emc": 64
    },
    {
      "item": "minecraft:cooked_mutton",
      "emc": 64
    },
    {
      "item": "xycraft_world:xychorium_gem_blue",
      "emc": 128
    },
    {
      "item": "xycraft_world:xychorium_gem_light",
      "emc": 128
    },
    {
      "item": "xycraft_world:xychorium_gem_dark",
      "emc": 128
    },
    {
      "item": "xycraft_world:xychorium_gem_red",
      "emc": 128
    },
    {
      "item": "xycraft_world:xychorium_gem_green",
      "emc": 128
    },
    {
      "item": "minecraft:bone_meal",
      "emc": 0
    },
    {
      "item": "minecraft:bone",
      "emc": 144
    },
    {
      "item": "minecraft:string",
      "emc": 12
    },
    {
      "item": "minecraft:gunpowder",
      "emc": 196
    },
    {
      "item": "minecraft:ghast_tear",
      "emc": 1024
    },
    {
      "item": "minecraft:acacia_log",
      "emc": 32
    },
    {
      "item": "minecraft:stripped_jungle_log",
      "emc": 32
    },
    {
      "item": "minecraft:jungle_log",
      "emc": 32
    },
    {
      "item": "minecraft:stripped_birch_log",
      "emc": 32
    },
    {
      "item": "minecraft:birch_log",
      "emc": 32
    },
    {
      "item": "minecraft:stripped_spruce_log",
      "emc": 32
    },
    {
      "item": "minecraft:spruce_log",
      "emc": 32
    },
    {
      "item": "minecraft:stripped_oak_log",
      "emc": 32
    },
    {
      "item": "minecraft:oak_log",
      "emc": 32
    },
    {
      "item": "minecraft:stripped_acacia_log",
      "emc": 32
    },
    {
      "item": "minecraft:dark_oak_log",
      "emc": 32
    },
    {
      "item": "minecraft:stripped_dark_oak_log",
      "emc": 32
    },
    {
      "item": "minecraft:mangrove_log",
      "emc": 32
    },
    {
      "item": "minecraft:stripped_mangrove_log",
      "emc": 32
    },
    {
      "item": "minecraft:cherry_log",
      "emc": 32
    },
    {
      "item": "minecraft:stripped_cherry_log",
      "emc": 32
    },
    {
      "item": "minecraft:crimson_stem",
      "emc": 32
    },
    {
      "item": "minecraft:stripped_crimson_stem",
      "emc": 32
    },
    {
      "item": "minecraft:light_gray_carpet",
      "emc": 32
    },
    {
      "item": "minecraft:gray_carpet",
      "emc": 32
    },
    {
      "item": "minecraft:black_carpet",
      "emc": 32
    },
    {
      "item": "minecraft:brown_carpet",
      "emc": 32
    },
    {
      "item": "minecraft:red_carpet",
      "emc": 32
    },
    {
      "item": "minecraft:orange_carpet",
      "emc": 32
    },
    {
      "item": "minecraft:yellow_carpet",
      "emc": 32
    },
    {
      "item": "minecraft:stripped_warped_stem",
      "emc": 32
    },
    {
      "item": "minecraft:warped_stem",
      "emc": 32
    },
    {
      "item": "minecraft:pink_carpet",
      "emc": 32
    },
    {
      "item": "minecraft:magenta_carpet",
      "emc": 32
    },
    {
      "item": "minecraft:purple_carpet",
      "emc": 32
    },
    {
      "item": "minecraft:blue_carpet",
      "emc": 32
    },
    {
      "item": "minecraft:light_blue_carpet",
      "emc": 32
    },
    {
      "item": "minecraft:cyan_carpet",
      "emc": 32
    },
    {
      "item": "minecraft:green_carpet",
      "emc": 32
    },
    {
      "item": "minecraft:lime_carpet",
      "emc": 32
    },
    {
      "item": "minecraft:white_carpet",
      "emc": 32
    },
    {
      "item": "minecraft:slime_ball",
      "emc": 32
    },
    {
      "item": "minecraft:rotten_flesh",
      "emc": 32
    },
    {
      "item": "minecraft:mangrove_planks",
      "emc": 8
    },
    {
      "item": "minecraft:dark_oak_planks",
      "emc": 8
    },
    {
      "item": "minecraft:acacia_planks",
      "emc": 8
    },
    {
      "item": "minecraft:jungle_planks",
      "emc": 8
    },
    {
      "item": "minecraft:birch_planks",
      "emc": 8
    },
    {
      "item": "minecraft:spruce_planks",
      "emc": 8
    },
    {
      "item": "minecraft:oak_planks",
      "emc": 8
    },
    {
      "item": "minecraft:crimson_planks",
      "emc": 8
    },
    {
      "item": "minecraft:warped_planks",
      "emc": 8
    },
    {
      "item": "minecraft:cherry_planks",
      "emc": 8
    },
    {
      "item": "minecraft:bamboo_planks",
      "emc": 8
    },
    {
      "item": "minecraft:green_wool",
      "emc": 48
    },
    {
      "item": "minecraft:white_wool",
      "emc": 48
    },
    {
      "item": "minecraft:light_gray_wool",
      "emc": 48
    },
    {
      "item": "minecraft:cyan_wool",
      "emc": 48
    },
    {
      "item": "minecraft:light_blue_wool",
      "emc": 48
    },
    {
      "item": "minecraft:blue_wool",
      "emc": 48
    },
    {
      "item": "minecraft:purple_wool",
      "emc": 48
    },
    {
      "item": "minecraft:magenta_wool",
      "emc": 48
    },
    {
      "item": "minecraft:pink_wool",
      "emc": 48
    },
    {
      "item": "minecraft:gray_wool",
      "emc": 48
    },
    {
      "item": "minecraft:lime_wool",
      "emc": 48
    },
    {
      "item": "minecraft:orange_wool",
      "emc": 48
    },
    {
      "item": "minecraft:red_wool",
      "emc": 48
    },
    {
      "item": "minecraft:brown_wool",
      "emc": 48
    },
    {
      "item": "minecraft:black_wool",
      "emc": 48
    },
    {
      "item": "minecraft:yellow_wool",
      "emc": 48
    },
    {
      "item": "minecraft:white_terracotta",
      "emc": 1
    },
    {
      "item": "minecraft:terracotta",
      "emc": 1
    },
    {
      "item": "minecraft:smooth_basalt",
      "emc": 1
    },
    {
      "item": "minecraft:basalt",
      "emc": 1
    },
    {
      "item": "minecraft:sandstone",
      "emc": 1
    },
    {
      "item": "minecraft:cobbled_deepslate",
      "emc": 1
    },
    {
      "item": "minecraft:deepslate",
      "emc": 1
    },
    {
      "item": "minecraft:cobblestone",
      "emc": 1
    },
    {
      "item": "minecraft:stone",
      "emc": 1
    },
    {
      "item": "minecraft:green_terracotta",
      "emc": 1
    },
    {
      "item": "minecraft:lime_terracotta",
      "emc": 1
    },
    {
      "item": "minecraft:yellow_terracotta",
      "emc": 1
    },
    {
      "item": "minecraft:orange_terracotta",
      "emc": 1
    },
    {
      "item": "minecraft:red_terracotta",
      "emc": 1
    },
    {
      "item": "minecraft:brown_terracotta",
      "emc": 1
    },
    {
      "item": "minecraft:black_terracotta",
      "emc": 1
    },
    {
      "item": "minecraft:gray_terracotta",
      "emc": 1
    },
    {
      "item": "minecraft:light_gray_terracotta",
      "emc": 1
    },
    {
      "item": "minecraft:pink_terracotta",
      "emc": 1
    },
    {
      "item": "minecraft:magenta_terracotta",
      "emc": 1
    },
    {
      "item": "minecraft:purple_terracotta",
      "emc": 1
    },
    {
      "item": "minecraft:blue_terracotta",
      "emc": 1
    },
    {
      "item": "minecraft:light_blue_terracotta",
      "emc": 1
    },
    {
      "item": "minecraft:cyan_terracotta",
      "emc": 1
    },
    {
      "item": "minecraft:cherry_leaves",
      "emc": 1
    },
    {
      "item": "minecraft:mangrove_leaves",
      "emc": 1
    },
    {
      "item": "minecraft:dark_oak_leaves",
      "emc": 1
    },
    {
      "item": "minecraft:acacia_leaves",
      "emc": 1
    },
    {
      "item": "minecraft:jungle_leaves",
      "emc": 1
    },
    {
      "item": "minecraft:birch_leaves",
      "emc": 1
    },
    {
      "item": "minecraft:spruce_leaves",
      "emc": 1
    },
    {
      "item": "minecraft:oak_leaves",
      "emc": 1
    },
    {
      "item": "minecraft:red_sand",
      "emc": 0
    },
    {
      "item": "minecraft:azalea_leaves",
      "emc": 1
    },
    {
      "item": "minecraft:moss_block",
      "emc": 1
    },
    {
      "item": "minecraft:moss_carpet",
      "emc": 1
    },
    {
      "item": "minecraft:netherrack",
      "emc": 0
    },
    {
      "item": "minecraft:calcite",
      "emc": 4
    },
    {
      "item": "minecraft:flower_pot",
      "emc": 4
    },
    {
      "item": "minecraft:clay",
      "emc": 4
    },
    {
      "item": "minecraft:nether_bricks",
      "emc": 4
    },
    {
      "item": "minecraft:red_sandstone",
      "emc": 4
    },
    {
      "item": "minecraft:bricks",
      "emc": 4
    },
    {
      "item": "minecraft:andesite",
      "emc": 1
    },
    {
      "item": "minecraft:diorite",
      "emc": 1
    },
    {
      "item": "minecraft:granite",
      "emc": 1
    },
    {
      "item": "minecraft:dripstone_block",
      "emc": 4
    },
    {
      "item": "create:limestone",
      "emc": 4
    },
    {
      "item": "minecraft:ink_sac",
      "emc": 16
    },
    {
      "item": "minecraft:spider_eye",
      "emc": 128
    },
    {
      "item": "minecraft:ochre_froglight",
      "emc": 256
    },
    {
      "item": "minecraft:verdant_froglight",
      "emc": 256
    },
    {
      "item": "minecraft:pearlescent_froglight",
      "emc": 256
    },
    {
      "item": "minecraft:leather",
      "emc": 27
    },
    {
      "item": "minecraft:blaze_powder",
      "emc": 0
    },
    {
      "item": "minecraft:blaze_rod",
      "emc": 1536
    },
    {
      "item": "projecte:interdiction_torch",
      "emc": 0
    },
    {
      "item": "projecte:transmutation_table",
      "emc": 260
    },
    {
      "item": "projecte:alchemical_chest",
      "emc": 0
    },
    {
      "item": "projecte:repair_talisman",
      "emc": 490
    },
    {
      "item": "projecte:black_alchemical_bag",
      "emc": 9851
    },
    {
      "item": "projecte:red_alchemical_bag",
      "emc": 9851
    },
    {
      "item": "projecte:green_alchemical_bag",
      "emc": 9851
    },
    {
      "item": "projecte:brown_alchemical_bag",
      "emc": 9851
    },
    {
      "item": "projecte:blue_alchemical_bag",
      "emc": 9851
    },
    {
      "item": "projecte:purple_alchemical_bag",
      "emc": 9851
    },
    {
      "item": "projecte:cyan_alchemical_bag",
      "emc": 9851
    },
    {
      "item": "projecte:light_gray_alchemical_bag",
      "emc": 9851
    },
    {
      "item": "projecte:gray_alchemical_bag",
      "emc": 9851
    },
    {
      "item": "projecte:pink_alchemical_bag",
      "emc": 9851
    },
    {
      "item": "projecte:lime_alchemical_bag",
      "emc": 9851
    },
    {
      "item": "projecte:yellow_alchemical_bag",
      "emc": 9851
    },
    {
      "item": "projecte:light_blue_alchemical_bag",
      "emc": 9851
    },
    {
      "item": "projecte:magenta_alchemical_bag",
      "emc": 9851
    },
    {
      "item": "projecte:orange_alchemical_bag",
      "emc": 9851
    },
    {
      "item": "projecte:white_alchemical_bag",
      "emc": 9851
    },
    {
      "item": "projecte:divining_rod_1",
      "emc": 12
    },
    {
      "item": "projecte:divining_rod_2",
      "emc": 76
    },
    {
      "item": "projecte:divining_rod_3",
      "emc": 1740
    },
    {
      "item": "projecte:low_covalence_dust",
      "emc": 1
    },
    {
      "item": "projecte:medium_covalence_dust",
      "emc": 5
    },
    {
      "item": "projecte:high_covalence_dust",
      "emc": 208
    },
    {
      "item": "minecraft:feather",
      "emc": 48
    },
    {
      "item": "minecraft:egg",
      "emc": 16
    },
    {
      "item": "minecraft:chicken",
      "emc": 64
    },
    {
      "item": "minecraft:cooked_chicken",
      "emc": 64
    },
    {
      "item": "minecraft:white_concrete",
      "emc": 1
    },
    {
      "item": "minecraft:light_gray_concrete",
      "emc": 1
    },
    {
      "item": "minecraft:gray_concrete",
      "emc": 1
    },
    {
      "item": "minecraft:black_concrete",
      "emc": 1
    },
    {
      "item": "minecraft:brown_concrete",
      "emc": 1
    },
    {
      "item": "minecraft:red_concrete",
      "emc": 1
    },
    {
      "item": "minecraft:orange_concrete",
      "emc": 1
    },
    {
      "item": "minecraft:yellow_concrete",
      "emc": 1
    },
    {
      "item": "minecraft:lime_concrete",
      "emc": 1
    },
    {
      "item": "minecraft:green_concrete",
      "emc": 1
    },
    {
      "item": "minecraft:cyan_concrete",
      "emc": 1
    },
    {
      "item": "minecraft:light_blue_concrete",
      "emc": 1
    },
    {
      "item": "minecraft:blue_concrete",
      "emc": 1
    },
    {
      "item": "minecraft:purple_concrete",
      "emc": 1
    },
    {
      "item": "minecraft:magenta_concrete",
      "emc": 1
    },
    {
      "item": "minecraft:pink_concrete",
      "emc": 1
    },
    {
      "item": "minecraft:glass",
      "emc": 1
    },
    {
      "item": "minecraft:ender_pearl",
      "emc": 1024
    },
    {
      "item": "minecraft:sea_lantern",
      "emc": 128
    },
    {
      "item": "minecraft:phantom_membrane",
      "emc": 2048
    },
    {
      "item": "mcwfences:acacia_hedge",
      "emc": 1
    },
    {
      "item": "mcwfences:acacia_highley_gate",
      "emc": 1
    },
    {
      "item": "mcwfences:acacia_horse_fence",
      "emc": 1
    },
    {
      "item": "mcwfences:acacia_picket_fence",
      "emc": 1
    },
    {
      "item": "mcwfences:acacia_pyramid_gate",
      "emc": 1
    },
    {
      "item": "mcwfences:acacia_stockade_fence",
      "emc": 1
    },
    {
      "item": "mcwfences:acacia_wired_fence",
      "emc": 1
    },
    {
      "item": "mcwfences:andesite_grass_topped_wall",
      "emc": 1
    },
    {
      "item": "mcwfences:andesite_pillar_wall",
      "emc": 1
    },
    {
      "item": "mcwfences:andesite_railing_gate",
      "emc": 1
    },
    {
      "item": "mcwfences:azalea_hedge",
      "emc": 1
    },
    {
      "item": "mcwfences:bamboo_fence",
      "emc": 1
    },
    {
      "item": "mcwfences:bamboo_highley_gate",
      "emc": 1
    },
    {
      "item": "mcwfences:bamboo_horse_fence",
      "emc": 1
    },
    {
      "item": "mcwfences:bamboo_picket_fence",
      "emc": 1
    },
    {
      "item": "mcwfences:bamboo_pyramid_gate",
      "emc": 1
    },
    {
      "item": "mcwfences:bamboo_stockade_fence",
      "emc": 1
    },
    {
      "item": "mcwfences:bamboo_wired_fence",
      "emc": 1
    },
    {
      "item": "mcwfences:birch_hedge",
      "emc": 1
    },
    {
      "item": "mcwfences:birch_highley_gate",
      "emc": 1
    },
    {
      "item": "mcwfences:birch_horse_fence",
      "emc": 1
    },
    {
      "item": "mcwfences:birch_picket_fence",
      "emc": 1
    },
    {
      "item": "mcwfences:birch_pyramid_gate",
      "emc": 1
    },
    {
      "item": "mcwfences:birch_stockade_fence",
      "emc": 1
    },
    {
      "item": "mcwfences:birch_wired_fence",
      "emc": 1
    },
    {
      "item": "mcwfences:blackstone_brick_railing_gate",
      "emc": 1
    },
    {
      "item": "mcwfences:blackstone_grass_topped_wall",
      "emc": 1
    },
    {
      "item": "mcwfences:blackstone_pillar_wall",
      "emc": 1
    },
    {
      "item": "mcwfences:blackstone_railing_gate",
      "emc": 1
    },
    {
      "item": "mcwfences:cherry_hedge",
      "emc": 1
    },
    {
      "item": "mcwfences:cherry_highley_gate",
      "emc": 1
    },
    {
      "item": "mcwfences:cherry_horse_fence",
      "emc": 1
    },
    {
      "item": "mcwfences:cherry_picket_fence",
      "emc": 1
    },
    {
      "item": "mcwfences:cherry_pyramid_gate",
      "emc": 1
    },
    {
      "item": "mcwfences:cherry_stockade_fence",
      "emc": 1
    },
    {
      "item": "mcwfences:cherry_wired_fence",
      "emc": 1
    },
    {
      "item": "mcwfences:crimson_highley_gate",
      "emc": 1
    },
    {
      "item": "mcwfences:crimson_horse_fence",
      "emc": 1
    },
    {
      "item": "mcwfences:crimson_picket_fence",
      "emc": 1
    },
    {
      "item": "mcwfences:crimson_pyramid_gate",
      "emc": 1
    },
    {
      "item": "mcwfences:crimson_stockade_fence",
      "emc": 1
    },
    {
      "item": "mcwfences:crimson_wired_fence",
      "emc": 1
    },
    {
      "item": "mcwfences:dark_oak_hedge",
      "emc": 1
    },
    {
      "item": "mcwfences:dark_oak_highley_gate",
      "emc": 1
    },
    {
      "item": "mcwfences:dark_oak_horse_fence",
      "emc": 1
    },
    {
      "item": "mcwfences:dark_oak_picket_fence",
      "emc": 1
    },
    {
      "item": "mcwfences:dark_oak_pyramid_gate",
      "emc": 1
    },
    {
      "item": "mcwfences:dark_oak_stockade_fence",
      "emc": 1
    },
    {
      "item": "mcwfences:dark_oak_wired_fence",
      "emc": 1
    },
    {
      "item": "mcwfences:deepslate_brick_grass_topped_wall",
      "emc": 1
    },
    {
      "item": "mcwfences:deepslate_brick_pillar_wall",
      "emc": 1
    },
    {
      "item": "mcwfences:deepslate_brick_railing_gate",
      "emc": 1
    },
    {
      "item": "mcwfences:deepslate_grass_topped_wall",
      "emc": 1
    },
    {
      "item": "mcwfences:deepslate_pillar_wall",
      "emc": 1
    },
    {
      "item": "mcwfences:deepslate_railing_gate",
      "emc": 1
    },
    {
      "item": "mcwfences:diorite_grass_topped_wall",
      "emc": 1
    },
    {
      "item": "mcwfences:diorite_pillar_wall",
      "emc": 1
    },
    {
      "item": "mcwfences:diorite_railing_gate",
      "emc": 1
    },
    {
      "item": "mcwfences:end_brick_grass_topped_wall",
      "emc": 1
    },
    {
      "item": "mcwfences:end_brick_pillar_wall",
      "emc": 1
    },
    {
      "item": "mcwfences:end_brick_railing_gate",
      "emc": 1
    },
    {
      "item": "mcwfences:flowering_azalea_hedge",
      "emc": 1
    },
    {
      "item": "mcwfences:granite_grass_topped_wall",
      "emc": 1
    },
    {
      "item": "mcwfences:granite_pillar_wall",
      "emc": 1
    },
    {
      "item": "mcwfences:granite_railing_gate",
      "emc": 1
    },
    {
      "item": "mcwfences:jungle_hedge",
      "emc": 1
    },
    {
      "item": "mcwfences:jungle_highley_gate",
      "emc": 1
    },
    {
      "item": "mcwfences:jungle_horse_fence",
      "emc": 1
    },
    {
      "item": "mcwfences:jungle_picket_fence",
      "emc": 1
    },
    {
      "item": "mcwfences:jungle_pyramid_gate",
      "emc": 1
    },
    {
      "item": "mcwfences:jungle_stockade_fence",
      "emc": 1
    },
    {
      "item": "mcwfences:jungle_wired_fence",
      "emc": 1
    },
    {
      "item": "mcwfences:mangrove_hedge",
      "emc": 1
    },
    {
      "item": "mcwfences:mangrove_highley_gate",
      "emc": 1
    },
    {
      "item": "mcwfences:mangrove_horse_fence",
      "emc": 1
    },
    {
      "item": "mcwfences:mangrove_picket_fence",
      "emc": 1
    },
    {
      "item": "mcwfences:mangrove_pyramid_gate",
      "emc": 1
    },
    {
      "item": "mcwfences:mangrove_stockade_fence",
      "emc": 1
    },
    {
      "item": "mcwfences:mangrove_wired_fence",
      "emc": 1
    },
    {
      "item": "mcwfences:modern_andesite_wall",
      "emc": 1
    },
    {
      "item": "mcwfences:modern_blackstone_wall",
      "emc": 1
    },
    {
      "item": "mcwfences:modern_deepslate_brick_wall",
      "emc": 1
    },
    {
      "item": "mcwfences:modern_deepslate_wall",
      "emc": 1
    },
    {
      "item": "mcwfences:modern_diorite_wall",
      "emc": 1
    },
    {
      "item": "mcwfences:modern_end_brick_wall",
      "emc": 1
    },
    {
      "item": "mcwfences:modern_granite_wall",
      "emc": 1
    },
    {
      "item": "mcwfences:modern_mud_brick_wall",
      "emc": 1
    },
    {
      "item": "mcwfences:modern_nether_brick_wall",
      "emc": 1
    },
    {
      "item": "mcwfences:modern_prismarine_wall",
      "emc": 1
    },
    {
      "item": "mcwfences:modern_quartz_wall",
      "emc": 1
    },
    {
      "item": "mcwfences:modern_red_sandstone_wall",
      "emc": 1
    },
    {
      "item": "mcwfences:modern_sandstone_wall",
      "emc": 1
    },
    {
      "item": "mcwfences:modern_stone_brick_wall",
      "emc": 1
    },
    {
      "item": "mcwfences:mud_brick_grass_topped_wall",
      "emc": 1
    },
    {
      "item": "mcwfences:mud_brick_pillar_wall",
      "emc": 1
    },
    {
      "item": "mcwfences:mud_brick_railing_gate",
      "emc": 1
    },
    {
      "item": "mcwfences:nether_brick_grass_topped_wall",
      "emc": 1
    },
    {
      "item": "mcwfences:nether_brick_pillar_wall",
      "emc": 1
    },
    {
      "item": "mcwfences:nether_brick_railing_gate",
      "emc": 1
    },
    {
      "item": "mcwfences:oak_hedge",
      "emc": 1
    },
    {
      "item": "mcwfences:oak_highley_gate",
      "emc": 1
    },
    {
      "item": "mcwfences:oak_horse_fence",
      "emc": 1
    },
    {
      "item": "mcwfences:oak_picket_fence",
      "emc": 1
    },
    {
      "item": "mcwfences:oak_pyramid_gate",
      "emc": 1
    },
    {
      "item": "mcwfences:oak_stockade_fence",
      "emc": 1
    },
    {
      "item": "mcwfences:oak_wired_fence",
      "emc": 1
    },
    {
      "item": "mcwfences:prismarine_grass_topped_wall",
      "emc": 1
    },
    {
      "item": "mcwfences:prismarine_pillar_wall",
      "emc": 1
    },
    {
      "item": "mcwfences:prismarine_railing_gate",
      "emc": 1
    },
    {
      "item": "mcwfences:quartz_grass_topped_wall",
      "emc": 1
    },
    {
      "item": "mcwfences:quartz_pillar_wall",
      "emc": 1
    },
    {
      "item": "mcwfences:quartz_railing_gate",
      "emc": 1
    },
    {
      "item": "mcwfences:railing_andesite_wall",
      "emc": 1
    },
    {
      "item": "mcwfences:railing_blackstone_wall",
      "emc": 1
    },
    {
      "item": "mcwfences:railing_deepslate_brick_wall",
      "emc": 1
    },
    {
      "item": "mcwfences:railing_deepslate_wall",
      "emc": 1
    },
    {
      "item": "mcwfences:railing_diorite_wall",
      "emc": 1
    },
    {
      "item": "mcwfences:railing_end_brick_wall",
      "emc": 1
    },
    {
      "item": "mcwfences:railing_granite_wall",
      "emc": 1
    },
    {
      "item": "mcwfences:railing_mud_brick_wall",
      "emc": 1
    },
    {
      "item": "mcwfences:railing_nether_brick_wall",
      "emc": 1
    },
    {
      "item": "mcwfences:railing_prismarine_wall",
      "emc": 1
    },
    {
      "item": "mcwfences:railing_quartz_wall",
      "emc": 1
    },
    {
      "item": "mcwfences:railing_red_sandstone_wall",
      "emc": 1
    },
    {
      "item": "mcwfences:railing_sandstone_wall",
      "emc": 1
    },
    {
      "item": "mcwfences:railing_stone_brick_wall",
      "emc": 1
    },
    {
      "item": "mcwfences:red_sandstone_grass_topped_wall",
      "emc": 1
    },
    {
      "item": "mcwfences:red_sandstone_pillar_wall",
      "emc": 1
    },
    {
      "item": "mcwfences:red_sandstone_railing_gate",
      "emc": 1
    },
    {
      "item": "mcwfences:sandstone_grass_topped_wall",
      "emc": 1
    },
    {
      "item": "mcwfences:sandstone_pillar_wall",
      "emc": 1
    },
    {
      "item": "mcwfences:sandstone_railing_gate",
      "emc": 1
    },
    {
      "item": "mcwfences:spruce_hedge",
      "emc": 1
    },
    {
      "item": "mcwfences:spruce_highley_gate",
      "emc": 1
    },
    {
      "item": "mcwfences:spruce_horse_fence",
      "emc": 1
    },
    {
      "item": "mcwfences:spruce_picket_fence",
      "emc": 1
    },
    {
      "item": "mcwfences:spruce_pyramid_gate",
      "emc": 1
    },
    {
      "item": "mcwfences:spruce_stockade_fence",
      "emc": 1
    },
    {
      "item": "mcwfences:spruce_wired_fence",
      "emc": 1
    },
    {
      "item": "mcwfences:stone_brick_railing_gate",
      "emc": 1
    },
    {
      "item": "mcwfences:stone_grass_topped_wall",
      "emc": 1
    },
    {
      "item": "mcwfences:stone_pillar_wall",
      "emc": 1
    },
    {
      "item": "mcwfences:warped_highley_gate",
      "emc": 1
    },
    {
      "item": "mcwfences:warped_horse_fence",
      "emc": 1
    },
    {
      "item": "mcwfences:warped_picket_fence",
      "emc": 1
    },
    {
      "item": "mcwfences:warped_pyramid_gate",
      "emc": 1
    },
    {
      "item": "mcwfences:warped_stockade_fence",
      "emc": 1
    },
    {
      "item": "mcwfences:warped_wired_fence",
      "emc": 1
    },
    {
      "item": "mcwfences:wooden_cheval_de_frise",
      "emc": 1
    },
    {
      "item": "mcwbridges:acacia_bridge_pier",
      "emc": 1
    },
    {
      "item": "mcwbridges:acacia_log_bridge_middle",
      "emc": 1
    },
    {
      "item": "mcwbridges:acacia_log_bridge_stair",
      "emc": 1
    },
    {
      "item": "mcwbridges:acacia_rail_bridge",
      "emc": 1
    },
    {
      "item": "mcwbridges:acacia_rope_bridge_stair",
      "emc": 1
    },
    {
      "item": "mcwbridges:andesite_bridge",
      "emc": 1
    },
    {
      "item": "mcwbridges:andesite_bridge_pier",
      "emc": 1
    },
    {
      "item": "mcwbridges:andesite_bridge_stair",
      "emc": 1
    },
    {
      "item": "mcwbridges:asian_red_bridge",
      "emc": 1
    },
    {
      "item": "mcwbridges:asian_red_bridge_pier",
      "emc": 1
    },
    {
      "item": "mcwbridges:asian_red_bridge_stair",
      "emc": 1
    },
    {
      "item": "mcwbridges:balustrade_andesite_bridge",
      "emc": 1
    },
    {
      "item": "mcwbridges:balustrade_blackstone_bridge",
      "emc": 1
    },
    {
      "item": "mcwbridges:balustrade_bricks_bridge",
      "emc": 1
    },
    {
      "item": "mcwbridges:balustrade_cobblestone_bridge",
      "emc": 1
    },
    {
      "item": "mcwbridges:balustrade_deepslate_bricks_bridge",
      "emc": 1
    },
    {
      "item": "mcwbridges:balustrade_deepslate_tiles_bridge",
      "emc": 1
    },
    {
      "item": "mcwbridges:balustrade_diorite_bridge",
      "emc": 1
    },
    {
      "item": "mcwbridges:balustrade_end_stone_bricks_bridge",
      "emc": 1
    },
    {
      "item": "mcwbridges:balustrade_granite_bridge",
      "emc": 1
    },
    {
      "item": "mcwbridges:balustrade_mossy_cobblestone_bridge",
      "emc": 1
    },
    {
      "item": "mcwbridges:balustrade_mossy_stone_bricks_bridge",
      "emc": 1
    },
    {
      "item": "mcwbridges:balustrade_mud_bricks_bridge",
      "emc": 1
    },
    {
      "item": "mcwbridges:balustrade_nether_bricks_bridge",
      "emc": 1
    },
    {
      "item": "mcwbridges:balustrade_orange_sandstone_bridge",
      "emc": 1
    },
    {
      "item": "mcwbridges:balustrade_prismarine_bricks_bridge",
      "emc": 1
    },
    {
      "item": "mcwbridges:balustrade_sandstone_bridge",
      "emc": 1
    },
    {
      "item": "mcwbridges:balustrade_stone_bricks_bridge",
      "emc": 1
    },
    {
      "item": "mcwbridges:bamboo_bridge",
      "emc": 1
    },
    {
      "item": "mcwbridges:bamboo_bridge_pier",
      "emc": 1
    },
    {
      "item": "mcwbridges:bamboo_bridge_stair",
      "emc": 1
    },
    {
      "item": "mcwbridges:birch_bridge_pier",
      "emc": 1
    },
    {
      "item": "mcwbridges:birch_log_bridge_middle",
      "emc": 1
    },
    {
      "item": "mcwbridges:birch_log_bridge_stair",
      "emc": 1
    },
    {
      "item": "mcwbridges:birch_rail_bridge",
      "emc": 1
    },
    {
      "item": "mcwbridges:birch_rope_bridge_stair",
      "emc": 1
    },
    {
      "item": "mcwbridges:blackstone_bridge",
      "emc": 1
    },
    {
      "item": "mcwbridges:blackstone_bridge_pier",
      "emc": 1
    },
    {
      "item": "mcwbridges:blackstone_bridge_stair",
      "emc": 1
    },
    {
      "item": "mcwbridges:brick_bridge",
      "emc": 1
    },
    {
      "item": "mcwbridges:brick_bridge_pier",
      "emc": 1
    },
    {
      "item": "mcwbridges:brick_bridge_stair",
      "emc": 1
    },
    {
      "item": "mcwbridges:cherry_bridge_pier",
      "emc": 1
    },
    {
      "item": "mcwbridges:cherry_log_bridge_middle",
      "emc": 1
    },
    {
      "item": "mcwbridges:cherry_log_bridge_stair",
      "emc": 1
    },
    {
      "item": "mcwbridges:cherry_rail_bridge",
      "emc": 1
    },
    {
      "item": "mcwbridges:cherry_rope_bridge_stair",
      "emc": 1
    },
    {
      "item": "mcwbridges:cobblestone_bridge",
      "emc": 1
    },
    {
      "item": "mcwbridges:cobblestone_bridge_pier",
      "emc": 1
    },
    {
      "item": "mcwbridges:cobblestone_bridge_stair",
      "emc": 1
    },
    {
      "item": "mcwbridges:crimson_bridge_pier",
      "emc": 1
    },
    {
      "item": "mcwbridges:crimson_log_bridge_middle",
      "emc": 1
    },
    {
      "item": "mcwbridges:crimson_log_bridge_stair",
      "emc": 1
    },
    {
      "item": "mcwbridges:crimson_rail_bridge",
      "emc": 1
    },
    {
      "item": "mcwbridges:crimson_rope_bridge_stair",
      "emc": 1
    },
    {
      "item": "mcwbridges:dark_oak_bridge_pier",
      "emc": 1
    },
    {
      "item": "mcwbridges:dark_oak_log_bridge_middle",
      "emc": 1
    },
    {
      "item": "mcwbridges:dark_oak_log_bridge_stair",
      "emc": 1
    },
    {
      "item": "mcwbridges:dark_oak_rail_bridge",
      "emc": 1
    },
    {
      "item": "mcwbridges:dark_oak_rope_bridge_stair",
      "emc": 1
    },
    {
      "item": "mcwbridges:deepslate_brick_bridge",
      "emc": 1
    },
    {
      "item": "mcwbridges:deepslate_brick_bridge_pier",
      "emc": 1
    },
    {
      "item": "mcwbridges:deepslate_brick_bridge_stair",
      "emc": 1
    },
    {
      "item": "mcwbridges:diorite_bridge",
      "emc": 1
    },
    {
      "item": "mcwbridges:diorite_bridge_pier",
      "emc": 1
    },
    {
      "item": "mcwbridges:diorite_bridge_stair",
      "emc": 1
    },
    {
      "item": "mcwbridges:dry_bamboo_bridge",
      "emc": 1
    },
    {
      "item": "mcwbridges:dry_bamboo_bridge_pier",
      "emc": 1
    },
    {
      "item": "mcwbridges:dry_bamboo_bridge_stair",
      "emc": 1
    },
    {
      "item": "mcwbridges:end_stone_bricks_bridge",
      "emc": 1
    },
    {
      "item": "mcwbridges:end_stone_bricks_bridge_pier",
      "emc": 1
    },
    {
      "item": "mcwbridges:end_stone_bricks_bridge_stair",
      "emc": 1
    },
    {
      "item": "mcwbridges:glass_bridge",
      "emc": 1
    },
    {
      "item": "mcwbridges:glass_bridge_pier",
      "emc": 1
    },
    {
      "item": "mcwbridges:glass_bridge_stair",
      "emc": 1
    },
    {
      "item": "mcwbridges:jungle_bridge_pier",
      "emc": 1
    },
    {
      "item": "mcwbridges:jungle_log_bridge_middle",
      "emc": 1
    },
    {
      "item": "mcwbridges:jungle_log_bridge_stair",
      "emc": 1
    },
    {
      "item": "mcwbridges:jungle_rail_bridge",
      "emc": 1
    },
    {
      "item": "mcwbridges:jungle_rope_bridge_stair",
      "emc": 1
    },
    {
      "item": "mcwbridges:mangrove_bridge_pier",
      "emc": 1
    },
    {
      "item": "mcwbridges:mangrove_log_bridge_middle",
      "emc": 1
    },
    {
      "item": "mcwbridges:mangrove_log_bridge_stair",
      "emc": 1
    },
    {
      "item": "mcwbridges:mangrove_rail_bridge",
      "emc": 1
    },
    {
      "item": "mcwbridges:mangrove_rope_bridge_stair",
      "emc": 1
    },
    {
      "item": "mcwbridges:mossy_cobblestone_bridge",
      "emc": 1
    },
    {
      "item": "mcwbridges:mossy_cobblestone_bridge_pier",
      "emc": 1
    },
    {
      "item": "mcwbridges:mossy_cobblestone_bridge_stair",
      "emc": 1
    },
    {
      "item": "mcwbridges:mossy_stone_brick_bridge",
      "emc": 1
    },
    {
      "item": "mcwbridges:mossy_stone_bridge_pier",
      "emc": 1
    },
    {
      "item": "mcwbridges:mossy_stone_bridge_stair",
      "emc": 1
    },
    {
      "item": "mcwbridges:mud_brick_bridge",
      "emc": 1
    },
    {
      "item": "mcwbridges:mud_brick_bridge_pier",
      "emc": 1
    },
    {
      "item": "mcwbridges:mud_brick_bridge_stair",
      "emc": 1
    },
    {
      "item": "mcwbridges:nether_bricks_bridge",
      "emc": 1
    },
    {
      "item": "mcwbridges:nether_bricks_bridge_pier",
      "emc": 1
    },
    {
      "item": "mcwbridges:nether_bricks_bridge_stair",
      "emc": 1
    },
    {
      "item": "mcwbridges:oak_bridge_pier",
      "emc": 1
    },
    {
      "item": "mcwbridges:oak_log_bridge_middle",
      "emc": 1
    },
    {
      "item": "mcwbridges:oak_log_bridge_stair",
      "emc": 1
    },
    {
      "item": "mcwbridges:oak_rail_bridge",
      "emc": 1
    },
    {
      "item": "mcwbridges:oak_rope_bridge_stair",
      "emc": 1
    },
    {
      "item": "mcwbridges:orange_sandstone_bridge",
      "emc": 1
    },
    {
      "item": "mcwbridges:pliers",
      "emc": 0
    },
    {
      "item": "mcwbridges:prismarine_bricks_bridge",
      "emc": 1
    },
    {
      "item": "mcwbridges:prismarine_bricks_bridge_pier",
      "emc": 1
    },
    {
      "item": "mcwbridges:prismarine_bricks_bridge_stair",
      "emc": 1
    },
    {
      "item": "mcwbridges:red_sandstone_bridge_pier",
      "emc": 1
    },
    {
      "item": "mcwbridges:red_sandstone_bridge_stair",
      "emc": 1
    },
    {
      "item": "mcwbridges:rope_acacia_bridge",
      "emc": 1
    },
    {
      "item": "mcwbridges:rope_birch_bridge",
      "emc": 1
    },
    {
      "item": "mcwbridges:rope_cherry_bridge",
      "emc": 1
    },
    {
      "item": "mcwbridges:rope_crimson_bridge",
      "emc": 1
    },
    {
      "item": "mcwbridges:rope_dark_oak_bridge",
      "emc": 1
    },
    {
      "item": "mcwbridges:rope_jungle_bridge",
      "emc": 1
    },
    {
      "item": "mcwbridges:rope_mangrove_bridge",
      "emc": 1
    },
    {
      "item": "mcwbridges:rope_oak_bridge",
      "emc": 1
    },
    {
      "item": "mcwbridges:rope_spruce_bridge",
      "emc": 1
    },
    {
      "item": "mcwbridges:rope_warped_bridge",
      "emc": 1
    },
    {
      "item": "mcwbridges:sandstone_bridge",
      "emc": 1
    },
    {
      "item": "mcwbridges:sandstone_bridge_pier",
      "emc": 1
    },
    {
      "item": "mcwbridges:sandstone_bridge_stair",
      "emc": 1
    },
    {
      "item": "mcwbridges:spruce_bridge_pier",
      "emc": 1
    },
    {
      "item": "mcwbridges:spruce_log_bridge_middle",
      "emc": 1
    },
    {
      "item": "mcwbridges:spruce_log_bridge_stair",
      "emc": 1
    },
    {
      "item": "mcwbridges:spruce_rail_bridge",
      "emc": 1
    },
    {
      "item": "mcwbridges:spruce_rope_bridge_stair",
      "emc": 1
    },
    {
      "item": "mcwbridges:stone_brick_bridge",
      "emc": 1
    },
    {
      "item": "mcwbridges:stone_brick_bridge_stair",
      "emc": 1
    },
    {
      "item": "mcwbridges:stone_bridge_pier",
      "emc": 1
    },
    {
      "item": "mcwbridges:warped_bridge_pier",
      "emc": 1
    },
    {
      "item": "mcwbridges:warped_log_bridge_middle",
      "emc": 1
    },
    {
      "item": "mcwbridges:warped_log_bridge_stair",
      "emc": 1
    },
    {
      "item": "mcwbridges:warped_rail_bridge",
      "emc": 1
    },
    {
      "item": "mcwbridges:warped_rope_bridge_stair",
      "emc": 1
    },
    {
      "item": "mcwfurnitures:acacia_bookshelf",
      "emc": 0
    },
    {
      "item": "mcwfurnitures:acacia_bookshelf_cupboard",
      "emc": 0
    },
    {
      "item": "mcwfurnitures:acacia_bookshelf_drawer",
      "emc": 0
    },
    {
      "item": "mcwfurnitures:acacia_chair",
      "emc": 0
    },
    {
      "item": "mcwfurnitures:acacia_coffee_table",
      "emc": 0
    },
    {
      "item": "mcwfurnitures:acacia_counter",
      "emc": 0
    },
    {
      "item": "mcwfurnitures:acacia_covered_desk",
      "emc": 0
    }
  ]
}